fast_version/__init__.py
fast_version/app.py
fast_version/helpers.py
fast_version/py.typed
fast_version/router.py
fast_version-1.4.4.dist-info/WHEEL
fast_version-1.4.4.dist-info/METADATA
fast_version-1.4.4.dist-info/RECORD
