Metadata-Version: 2.4
Name: fast-version
Version: 1.4.4
Summary: Fastapi versioning package with accept header
Keywords: fastapi,versioning,accept-header
Author: Artur Shiriev
Author-email: Artur Shiriev <me@shiriev.ru>
License-Expression: MIT
Classifier: Programming Language :: Python :: 3.10
Classifier: Programming Language :: Python :: 3.11
Classifier: Programming Language :: Python :: 3.12
Classifier: Programming Language :: Python :: 3.13
Classifier: Programming Language :: Python :: 3.14
Classifier: Typing :: Typed
Classifier: Topic :: Software Development :: Libraries
Requires-Dist: fastapi>=0.100
Requires-Python: >=3.10, <4
Project-URL: repository, https://github.com/modern-python/fast-version
